<annotation>
	<folder>AppBar</folder>
	<filename>appbar_2.png</filename>
	<path>C:\Users\jeetk\OneDrive\Desktop\Classes\AppBar\appbar_2.png</path>
	<source>
		<database>Unknown</database>
	</source>
	<size>
		<width>400</width>
		<height>868</height>
		<depth>3</depth>
	</size>
	<segmented>0</segmented>
	<object>
		<name>AppBar</name>
		<pose>Unspecified</pose>
		<truncated>1</truncated>
		<difficult>0</difficult>
		<bndbox>
			<xmin>1</xmin>
			<ymin>35</ymin>
			<xmax>400</xmax>
			<ymax>87</ymax>
		</bndbox>
	</object>
</annotation>
